Metadata-Version: 1.1
Name: idealista-api-python
Version: 0.1.2
Summary: Upload properties to Idealista using IDEALISTA API.
Home-page: https://bitbucket.org/abalt/idealista-api-python
Author: DNest
Author-email: admin@dnestagency.com
License: Copyright (c) 2011, Tangent Communications PLC and individual contributors.
